cosinnus_notifications/__init__.py
cosinnus_notifications/admin.py
cosinnus_notifications/apps.py
cosinnus_notifications/cosinnus_app.py
cosinnus_notifications/digest.py
cosinnus_notifications/forms.py
cosinnus_notifications/hooks.py
cosinnus_notifications/models.py
cosinnus_notifications/notifications.py
cosinnus_notifications/urls.py
cosinnus_notifications/views.py
cosinnus_notifications/locale/de/LC_MESSAGES/django.mo
cosinnus_notifications/locale/de/LC_MESSAGES/django.po
cosinnus_notifications/locale/en/LC_MESSAGES/django.mo
cosinnus_notifications/locale/en/LC_MESSAGES/django.po
cosinnus_notifications/locale/fr/LC_MESSAGES/django.mo
cosinnus_notifications/locale/fr/LC_MESSAGES/django.po
cosinnus_notifications/locale/ru/LC_MESSAGES/django.mo
cosinnus_notifications/locale/ru/LC_MESSAGES/django.po
cosinnus_notifications/locale/uk/LC_MESSAGES/django.mo
cosinnus_notifications/locale/uk/LC_MESSAGES/django.po
cosinnus_notifications/management/__init__.py
cosinnus_notifications/management/commands/__init__.py
cosinnus_notifications/management/commands/send_daily_digest.py
cosinnus_notifications/management/commands/send_weekly_digest.py
cosinnus_notifications/migrations/0001_initial.py
cosinnus_notifications/migrations/0002_auto_20160125_1339.py
cosinnus_notifications/migrations/0003_usernotificationpreference_setting.py
cosinnus_notifications/migrations/0004_transform_is_active_to_setting.py
cosinnus_notifications/migrations/0005_remove_usernotificationpreference_is_active.py
cosinnus_notifications/migrations/0006_notificationevent.py
cosinnus_notifications/migrations/__init__.py
cosinnus_notifications/static/css/cosinnus_notifications.css
cosinnus_notifications/templates/cosinnus_notifications/base.html
cosinnus_notifications/templates/cosinnus_notifications/notifications_form.html
cosinnus_notifications-0.6.dev20180228171223.data/data/cosinnus_notifications/locale/de/LC_MESSAGES/django.mo
cosinnus_notifications-0.6.dev20180228171223.dist-info/DESCRIPTION.rst
cosinnus_notifications-0.6.dev20180228171223.dist-info/METADATA
cosinnus_notifications-0.6.dev20180228171223.dist-info/RECORD
cosinnus_notifications-0.6.dev20180228171223.dist-info/WHEEL
cosinnus_notifications-0.6.dev20180228171223.dist-info/metadata.json
cosinnus_notifications-0.6.dev20180228171223.dist-info/top_level.txt
